<?xml version="1.0" encoding="utf-8"?>
<!DOCTYPE hibernate-mapping PUBLIC "-//Hibernate/Hibernate Mapping DTD 3.0//EN"
"http://hibernate.sourceforge.net/hibernate-mapping-3.0.dtd">
<!-- 
    Mapping file autogenerated by MyEclipse Persistence Tools
-->
<hibernate-mapping>
    <class name="com.portal.model.GridSearch" table="pt_gridsearch" catalog="portal">
        <id name="id" type="integer">
            <column name="id" />
            <generator class="identity"></generator>
        </id>
        <many-to-one name="gridPortletDescription" class="com.portal.model.GridPortletDescription" fetch="select">
            <column name="gridPortletDescription_id" not-null="true" />
        </many-to-one>
        <property name="searchName" type="string">
            <column name="searchName" length="100" not-null="true" />
        </property>
        <property name="searchType" type="string">
            <column name="searchType" length="30" not-null="true">
                <comment>gt lt ge le eq like</comment>
            </column>
        </property>
        <property name="searchDesc" type="string">
            <column name="searchDesc" length="300" />
        </property>
    </class>
</hibernate-mapping>
